<annotation>
	<folder>images</folder>
	<filename>andres-gomez-tlKTvMlu_fA-unsplash.jpg</filename>
	<path>E:\my_project\YOLO\images\andres-gomez-tlKTvMlu_fA-unsplash.jpg</path>
	<source>
		<database>Unknown</database>
	</source>
	<size>
		<width>3374</width>
		<height>4906</height>
		<depth>3</depth>
	</size>
	<segmented>0</segmented>
	<object>
		<name>chair</name>
		<pose>Unspecified</pose>
		<truncated>0</truncated>
		<difficult>0</difficult>
		<bndbox>
			<xmin>1070</xmin>
			<ymin>2003</ymin>
			<xmax>2520</xmax>
			<ymax>4411</ymax>
		</bndbox>
	</object>
</annotation>
